<?xml version="1.0" encoding="UTF-8"?>
<!DOCTYPE suite SYSTEM "http://testng.org/testng-1.0.dtd">
<suite name="All Test Suite">
    <groups>
        <run>
            <include name="qa"></include>
        </run>
    </groups>
    <test verbose="2" preserve-order="true" name="C:/Users/rnish/Development/workspcae2024/APIAutomationFrameworkATB8X">
        <classes>
            <class name="com.theTestingacademy.test.Integration.Sample.TestIntegrationSample">
                <methods>
                    <include name="testCreateBooking"/>
                    <include name="testVerifyBookingId"/>
                    <include name="testUpdateBookingByID"/>
                    <include name="testDeleteBookingById"/>
                </methods>
            </class>
        </classes>
    </test>
</suite>